KNet/__init__.py
KNet/app.py
KNet/main.py
KNet/cli/__init__.py
KNet/cli/commands.py
KNet/lib/__init__.py
KNet/lib/cleanup.sh
KNet/lib/docker_cmds.py
KNet/lib/host.py
KNet/lib/link.py
KNet/lib/logger.py
KNet/lib/networks.py
KNet/lib/ovs_cmds.py
KNet/lib/qos.py
KNet/lib/router.py
KNet/lib/schema.py
KNet/lib/server.py
KNet/lib/switches.py
KNet/lib/tc_cmds.py
KNet/lib/topology.py
KNet/lib/utils.py
KNet/test/__init__.py
KNet/test/testutils.py
KNet-1.0.15.dist-info/DESCRIPTION.rst
KNet-1.0.15.dist-info/METADATA
KNet-1.0.15.dist-info/RECORD
KNet-1.0.15.dist-info/WHEEL
KNet-1.0.15.dist-info/entry_points.txt
KNet-1.0.15.dist-info/metadata.json
KNet-1.0.15.dist-info/top_level.txt
