Metadata-Version: 2.0
Name: KNet
Version: 1.0.15
Summary: Virtual Network Topology Builder
Home-page: https://github.com/knetsolutions/KNet
Author: KNet Solutions
Author-email: knetsolutions2@gmail.com
License: Apache
Keywords: sdn
Platform: UNKNOWN
Classifier: Development Status :: 4 - Beta
Classifier: Intended Audience :: Developers
Classifier: Topic :: Software Development :: User Interfaces
Classifier: Programming Language :: Python :: 2.7
Requires-Python: >=2.6, <3
Requires-Dist: beautifultable (==0.3.0)
Requires-Dist: flask (==0.12.3)
Requires-Dist: ipaddress (==1.0.19)
Requires-Dist: jsonschema (==2.6.0)
Requires-Dist: logger (==1.4)
Requires-Dist: pyyaml (==4.2b1)
Requires-Dist: six (==1.11.0)
Requires-Dist: smallcli (==0.1)
Requires-Dist: tinydb (==3.7.0)
